A2/1/one_bit_alu.v
// Assignment by Narayan G 17CO225 and Dhanasekhar M 17CO214
// Date - 25-10-2018
// One bit ALU


module one_bit_alu (a,b,a_invert,b_invert,operation,result,carry_in,zf,carry_out) ;

	input a,b,a_invert,b_invert,carry_in;
	input [1:0] operation;
	output result,zf,carry_out;

	reg result, zf, sum, and_, or_, b_out, a_out, carry_out, less_o;

	always @(a,b,a_invert,b_invert,operation,carry_in) begin

		a_out = a ^ a_invert;																	//a_out represents the final output of a after inversion
		b_out = b ^ b_invert;																	//b_out represents the final output of b after inversion
	
		sum = (a_out ^ b_out) ^ (carry_in) ;													//All outputs are stored in variables
		and_ = a_out & b_out;
		or_ = a_out | b_out;

		case(operation)
			2'b00 : result = and_;																//Suitable output is chosen
			2'b01 : result = or_;
			2'b10 : result = sum;
		endcase
		carry_out = (a_out & b_out) | (b_out & carry_in) | (carry_in & a_out);
		zf = ~result ;
	end


endmodule

A2/1/one_bit_alu_tb.v
// Assignment by Narayan G 17CO225 and Dhanasekhar M 17CO214
// Date - 25-10-2018
// One bit ALU


`include "one_bit_alu.v"
module one_bit_alu_tb();

	reg a, b, a_invert, b_invert, carry_in;
	reg [1:0] operation;
	wire result, zf, carry_out;

	one_bit_alu DUT(.a(a),.b(b),.a_invert(a_invert),.b_invert(b_invert),.operation(operation),.result(result), .carry_in(carry_in), .zf(zf), .carry_out(carry_out));

	initial begin

		$dumpfile("wave.vcd");
		$dumpvars();

		a=0; b=0; a_invert = 0; b_invert = 0; carry_in = 0;
		operation = 2'b00;																		// Operation 00 is for AND gate

		#10
		a=1;

		#10
		a=0; b=1;
		
		#10
		a=1; b=1;

		#10 a=0; b=0; a_invert = 0; b_invert = 0; carry_in = 0;									// Operation 01 is for OR
		operation = 2'b01;

		#10
		a=1;

		#10
		a=0; b=1;
		
		#10
		a=1; b=1;

		#10 a=0; b=0; a_invert = 0; b_invert = 0; carry_in = 0;									// Operation 10 is for XOR
		operation = 2'b10;

		#10
		a=1;

		#10
		a=0; b=1;
		
		#10
		a=1; b=1;


		#10
		$finish;
	end

	initial begin
		$display("a\tb\toperation\tresult\tZeroFlag");
		$monitor("%b\t%b\t   %b   \t%b\t%b",a,b,operation,result,zf);
	end

endmodule

A2/1/wave.vcd
$date
	Thu Oct 25 19:32:04 2018
$end
$version
	Icarus Verilog
$end
$timescale
	1s
$end
$scope module one_bit_alu_tb $end
$var wire 1 ! zf $end
$var wire 1 " result $end
$var wire 1 # carry_out $end
$var reg 1 $ a $end
$var reg 1 % a_invert $end
$var reg 1 & b $end
$var reg 1 ' b_invert $end
$var reg 1 ( carry_in $end
$var reg 2 ) operation [1:0] $end
$scope module DUT $end
$var wire 1 $ a $end
$var wire 1 % a_invert $end
$var wire 1 & b $end
$var wire 1 ' b_invert $end
$var wire 1 ( carry_in $end
$var wire 2 * operation [1:0] $end
$var reg 1 + a_out $end
$var reg 1 , and_ $end
$var reg 1 - b_out $end
$var reg 1 # carry_out $end
$var reg 1 . or_ $end
$var reg 1 " result $end
$var reg 1 / sum $end
$var reg 1 ! zf $end
$upscope $end
$upscope $end
$enddefinitions $end
#0
$dumpvars
0/
0.
0-
0,
0+
b0 *
b0 )
0(
0'
0&
0%
0$
0#
0"
1!
$end
#10
1.
1/
1+
1$
#20
1-
0+
1&
0$
#30
0!
1#
1"
1,
0/
1+
1$
#40
1!
0#
0"
0.
0,
0-
0+
b1 )
b1 *
0&
0$
#50
0!
1"
1.
1/
1+
1$
#60
1-
0+
1&
0$
#70
1#
1,
0/
1+
1$
#80
1!
0#
0"
0.
0,
0-
0+
b10 )
b10 *
0&
0$
#90
0!
1"
1.
1/
1+
1$
#100
1-
0+
1&
0$
#110
1!
1#
0"
1,
0/
1+
1$
