A3/A3/1/mcu.v
//Name : 	Nishanth Subramanian		Narayan G	
//Roll No : 171CO127					171CO225
//Date : January 8 2019
//MAIN CONTROL UNIT


module mcu(input [31:0]instruction, output alusrc, output memtoreg, output regwrite, output memread, output memwrite, output branch, output aluop1, output aluop2);
	
	assign alusrc = ~instruction[5] || ((~instruction[6])&&(~instruction[4])); 
	assign memtoreg = ~instruction[4];
	assign regwrite = ~instruction[5] || instruction[4] ;
	assign memread = (~instruction[5])&&(~instruction[4]);
	assign memwrite = (~instruction[6])&&(instruction[5])&&(~instruction[4]) ;
	assign branch = instruction[6] ;
	assign aluop1 = instruction[4] ;
	assign aluop2 = instruction[6] ;
	
endmodule

A3/A3/1/mcu_tb.v
//Name : 	Nishanth Subramanian		Narayan G	
//Roll No : 171CO127					171CO225
//Date : January 8 2019
//FULL DATAPATH


`include "mcu.v"

module mcu_tb();

	reg [31:0]instruction;
	wire alusrc;
	wire memtoreg;
	wire regwrite;
	wire memread;
	wire memwrite;
	wire branch;
	wire aluop1;
	wire aluop2;
	
	mcu DUT(instruction, alusrc, memtoreg, regwrite, memread, memwrite, branch, aluop1, aluop2);
	
	initial
		begin
			$dumpfile("wave.vcd");
			$dumpvars();
		
			instruction = 32'b 00000000000001001011000100000011;
			#10 instruction = 32'b 00000000010001001011000010000011;
			#10 instruction = 32'b 00000000001000001000011001100011;
			#10 instruction = 32'b 01000000000100010000000110110011;
			#10 instruction = 32'b 00000000100100011000010000100011;
			#10 instruction = 32'b 11111110011100010000000110010011;
			#10 instruction = 32'b 00000000100100011000010000100011;
			#10 instruction = 32'b 00000000000000011011001100000011;

			#10 $finish;
	
		end
		
		initial
			begin
		
				$display("Instruction\t\t\t\tAlusrc\tMemtoReg\tRegWrite\tMemRead\t\tMemWrite\tBranch\top1\top2");
				$monitor("%b\t%b\t%b\t\t%b\t\t%b\t\t%b\t\t%b\t%b\t%b",instruction, alusrc, memtoreg, regwrite, memread, memwrite, branch, aluop1, aluop2);
		
			end


endmodule

A3/A3/1/wave.vcd
$date
	Sun Jan 20 23:31:35 2019
$end
$version
	Icarus Verilog
$end
$timescale
	1s
$end
$scope module mcu_tb $end
$var wire 1 ! regwrite $end
$var wire 1 " memwrite $end
$var wire 1 # memtoreg $end
$var wire 1 $ memread $end
$var wire 1 % branch $end
$var wire 1 & alusrc $end
$var wire 1 ' aluop2 $end
$var wire 1 ( aluop1 $end
$var reg 32 ) instruction [31:0] $end
$scope module DUT $end
$var wire 1 & alusrc $end
$var wire 32 * instruction [31:0] $end
$var wire 1 $ memread $end
$var wire 1 # memtoreg $end
$var wire 1 " memwrite $end
$var wire 1 ! regwrite $end
$var wire 1 % branch $end
$var wire 1 ' aluop2 $end
$var wire 1 ( aluop1 $end
$upscope $end
$upscope $end
$enddefinitions $end
#0
$dumpvars
b1001011000100000011 *
b1001011000100000011 )
0(
0'
1&
0%
1$
1#
0"
1!
$end
#10
b10001001011000010000011 )
b10001001011000010000011 *
#20
0&
0!
0$
0"
1%
1'
b1000001000011001100011 )
b1000001000011001100011 *
#30
0#
1!
0%
1(
0'
b1000000000100010000000110110011 )
b1000000000100010000000110110011 *
#40
1&
1"
1#
0!
0(
b100100011000010000100011 )
b100100011000010000100011 *
#50
0"
0#
1!
1(
b11111110011100010000000110010011 )
b11111110011100010000000110010011 *
#60
0!
1"
1#
0(
b100100011000010000100011 )
b100100011000010000100011 *
#70
1!
1$
0"
b11011001100000011 )
b11011001100000011 *
